README.md
setup.cfg
setup.py
el_logging/__init__.py
el_logging/__version__.py
el_logging/logging.py
el_logging.egg-info/PKG-INFO
el_logging.egg-info/SOURCES.txt
el_logging.egg-info/dependency_links.txt
el_logging.egg-info/requires.txt
el_logging.egg-info/top_level.txt