Metadata-Version: 2.1
Name: el-logging
Version: 0.2.22
Summary: Loguru based custom logging package for simple python projects.
Home-page: https://bitbucket.org/ellexiinc/el_logging/
Author: Batkhuu Byambajav
Author-email: batkhuu@ellexi.com
License: MIT
Download-URL: https://bitbucket.org/ellexiinc/el_logging/get/release-0.2.22.tar.gz
Keywords: el_logging,loguru,logging,logger,logs,log,print,custom logging
Platform: UNKNOWN
Classifier: Development Status :: 3 - Alpha
Classifier: Intended Audience :: Developers
Classifier: Topic :: Software Development :: Build Tools
Classifier: License :: OSI Approved :: MIT License
Classifier: Programming Language :: Python :: 3.6
Classifier: Programming Language :: Python :: 3.7
